localcosmos_cordova_builder/AppImageCreator.py
localcosmos_cordova_builder/CordovaAppBuilder.py
localcosmos_cordova_builder/JobManager.py
localcosmos_cordova_builder/MetaAppDefinition.py
localcosmos_cordova_builder/__init__.py
localcosmos_cordova_builder/image_utils.py
localcosmos_cordova_builder/logger.py
localcosmos_cordova_builder/required_assets.py
localcosmos_cordova_builder/urllib_request_upload_files.py
localcosmos_cordova_builder/resources/__init__.py
localcosmos_cordova_builder/resources/images/__init__.py
localcosmos_cordova_builder/resources/images/adaptive_launcher_background.png
localcosmos_cordova_builder/resources/images/adaptive_launcher_background.svg
localcosmos_cordova_builder/resources/images/appLauncherIcon.svg
localcosmos_cordova_builder-0.9.6.dist-info/licenses/LICENSE
localcosmos_cordova_builder-0.9.6.dist-info/METADATA
localcosmos_cordova_builder-0.9.6.dist-info/WHEEL
localcosmos_cordova_builder-0.9.6.dist-info/top_level.txt
localcosmos_cordova_builder-0.9.6.dist-info/RECORD
